LICENSE
azdebugrelay/__init__.py
azdebugrelay/debug_relay.py
azdebugrelay/debugpyex.py
azdebugrelay/threads.py
azure_debug_relay-0.5.1.dist-info/LICENSE
azure_debug_relay-0.5.1.dist-info/WHEEL
azure_debug_relay-0.5.1.dist-info/METADATA
azure_debug_relay-0.5.1.dist-info/RECORD
