Metadata-Version: 2.1
Name: azure-debug-relay
Version: 0.5.1
Summary: Azure Debugging Relay: distributed cross-network remote debugging for Python
License: MIT
Keywords: debug,remote,azure
Author: Vlad Kolesnikov
Requires-Python: >=3.6,<4.0
Classifier: License :: OSI Approved :: MIT License
Classifier: Programming Language :: Python :: 3
Classifier: Programming Language :: Python :: 3.6
Classifier: Programming Language :: Python :: 3.7
Classifier: Programming Language :: Python :: 3.8
Classifier: Programming Language :: Python :: 3.9
Requires-Dist: debugpy (>=1.2.1,<2.0.0)
